MANIFEST.in
README.md
requirements.txt
setup.cfg
setup.py
datatableview/__init__.py
datatableview/cache.py
datatableview/columns.py
datatableview/compat.py
datatableview/datatables.py
datatableview/exceptions.py
datatableview/forms.py
datatableview/helpers.py
datatableview/models.py
datatableview/utils.py
datatableview/static/js/datatableview.js
datatableview/static/js/datatableview.min.js
datatableview/templates/datatableview/bootstrap_structure.html
datatableview/templates/datatableview/default_structure.html
datatableview/templates/datatableview/legacy_structure.html
datatableview/tests/__init__.py
datatableview/tests/test_columns.py
datatableview/tests/test_datatables.py
datatableview/tests/test_helpers.py
datatableview/tests/test_utils.py
datatableview/tests/test_views.py
datatableview/tests/testcase.py
datatableview/tests/example_project/__init__.py
datatableview/tests/example_project/manage.py
datatableview/tests/example_project/example_project/__init__.py
datatableview/tests/example_project/example_project/settings.py
datatableview/tests/example_project/example_project/urls.py
datatableview/tests/example_project/example_project/wsgi.py
datatableview/tests/example_project/example_project/example_app/__init__.py
datatableview/tests/example_project/example_project/example_app/models.py
datatableview/tests/example_project/example_project/example_app/urls.py
datatableview/tests/example_project/example_project/example_app/views.py
datatableview/tests/example_project/example_project/example_app/migrations/0001_initial.py
datatableview/tests/example_project/example_project/example_app/migrations/0002_entry_is_published.py
datatableview/tests/example_project/example_project/example_app/migrations/__init__.py
datatableview/tests/example_project/example_project/example_app/templatetags/__init__.py
datatableview/tests/example_project/example_project/example_app/templatetags/example_app_tags.py
datatableview/tests/test_app/__init__.py
dtv_custom.egg-info/PKG-INFO
dtv_custom.egg-info/SOURCES.txt
dtv_custom.egg-info/dependency_links.txt
dtv_custom.egg-info/requires.txt
dtv_custom.egg-info/top_level.txt