Metadata-Version: 2.1
Name: dtv-custom
Version: 0.0.1
Summary: This package is used in conjunction with the jQuery plugin (http://http://datatables.net/), and supports state-saving detection with (http://datatables.net/plug-ins/api).  The package consists of a class-based view, and a small collection of utilities for rendering table data from models.
Home-page: https://github.com/packerbacker3333/django-datatable-view
Author: John Raleigh
Author-email: john.j.raleigh@gmail.com
License: Apache License (2.0)
Download-URL: https://github.com/packerbacker3333/django-datatable-view/archive/jjr-0.0.1.tar.gz
Platform: UNKNOWN
Classifier: Development Status :: 2 - Pre-Alpha
Classifier: Environment :: Web Environment
Classifier: Framework :: Django
Classifier: Intended Audience :: Developers
Classifier: License :: OSI Approved :: Apache Software License
Classifier: Operating System :: OS Independent
Classifier: Programming Language :: Python
Classifier: Topic :: Software Development
